fastdc/__init__.py
fastdc/bot.py
fastdc/trainer.py
fastdc-1.8.dist-info/LICENSE
fastdc-1.8.dist-info/METADATA
fastdc-1.8.dist-info/WHEEL
fastdc-1.8.dist-info/top_level.txt
fastdc-1.8.dist-info/RECORD
