Metadata-Version: 2.1
Name: fastdc
Version: 1.8
Summary: Fastdc is a library designed to make creating Discord bots easier.
Home-page: UNKNOWN
Author: Arya Wiratama
Author-email: aryawiratama2401@gmail.com
License: UNKNOWN
Platform: UNKNOWN
Requires-Python: >=3.10
License-File: LICENSE
Requires-Dist: SQLAlchemy>=2.0.0
Requires-Dist: aiohttp>=3.8.0
Requires-Dist: chatterbot-corpus>=1.2.0
Requires-Dist: chatterbot>=1.0.0
Requires-Dist: discord.py>=2.3.0
Requires-Dist: groq>=0.3.0
Requires-Dist: openai>=1.0.0
Requires-Dist: python-dotenv>=1.0.0
Requires-Dist: spacy>=3.0.0
